_quickfix.cp310-win_amd64.pyd
quickfix.py
quickfix40.py
quickfix41.py
quickfix42.py
quickfix43.py
quickfix44.py
quickfix50.py
quickfix50sp1.py
quickfix50sp2.py
quickfixt11.py
qfx-1.15.1.data/data/share/quickfix/FIX40.xml
qfx-1.15.1.data/data/share/quickfix/FIX41.xml
qfx-1.15.1.data/data/share/quickfix/FIX42.xml
qfx-1.15.1.data/data/share/quickfix/FIX43.xml
qfx-1.15.1.data/data/share/quickfix/FIX44.xml
qfx-1.15.1.data/data/share/quickfix/FIX50.xml
qfx-1.15.1.data/data/share/quickfix/FIX50SP1.xml
qfx-1.15.1.data/data/share/quickfix/FIX50SP2.xml
qfx-1.15.1.data/data/share/quickfix/FIXT11.xml
qfx-1.15.1.dist-info/LICENSE
qfx-1.15.1.dist-info/METADATA
qfx-1.15.1.dist-info/WHEEL
qfx-1.15.1.dist-info/top_level.txt
qfx-1.15.1.dist-info/RECORD
